.checkstyle
.project
.pydevproject
ChangeLog
LICENSE
MANIFEST.in
README
setup.cfg
setup.py
.settings/org.eclipse.wst.sse.core.prefs
.settings/org.eclipse.wst.validation.prefs
doc/pycrypt.pdf
doc/pycrypt.tex
jtestdata/aes/1
jtestdata/aes/1.out
jtestdata/aes/2
jtestdata/aes/2.out
jtestdata/aes/meta
jtestdata/aes-crypted/1
jtestdata/aes-crypted/1.out
jtestdata/aes-crypted/2
jtestdata/aes-crypted/2.out
jtestdata/aes-crypted/meta
jtestdata/dsa/1
jtestdata/dsa/1.out
jtestdata/dsa/2
jtestdata/dsa/2.out
jtestdata/dsa/meta
jtestdata/dsa.public/1
jtestdata/dsa.public/2
jtestdata/dsa.public/meta
jtestdata/hmac/1
jtestdata/hmac/1.out
jtestdata/hmac/2
jtestdata/hmac/2.out
jtestdata/hmac/meta
jtestdata/rsa/1
jtestdata/rsa/1.out
jtestdata/rsa/2
jtestdata/rsa/2.out
jtestdata/rsa/meta
jtestdata/rsa-sign/1
jtestdata/rsa-sign/1.out
jtestdata/rsa-sign/2
jtestdata/rsa-sign/2.out
jtestdata/rsa-sign/meta
jtestdata/rsa-sign.public/1
jtestdata/rsa-sign.public/2
jtestdata/rsa-sign.public/meta
python_keyczar.egg-info/PKG-INFO
python_keyczar.egg-info/SOURCES.txt
python_keyczar.egg-info/dependency_links.txt
python_keyczar.egg-info/entry_points.txt
python_keyczar.egg-info/requires.txt
python_keyczar.egg-info/top_level.txt
src/keyczar/__init__.py
src/keyczar/errors.py
src/keyczar/keyczar.py
src/keyczar/keyczart.py
src/keyczar/keydata.py
src/keyczar/keyinfo.py
src/keyczar/keys.py
src/keyczar/readers.py
src/keyczar/util.py
src/keyczar/writers.py
testdata/aes/1
testdata/aes/1.out
testdata/aes/2
testdata/aes/2.out
testdata/aes/meta
testdata/aes-crypted/1
testdata/aes-crypted/1.out
testdata/aes-crypted/2
testdata/aes-crypted/2.out
testdata/aes-crypted/meta
testdata/dsa/1
testdata/dsa/1.out
testdata/dsa/2
testdata/dsa/2.out
testdata/dsa/meta
testdata/dsa.public/1
testdata/dsa.public/2
testdata/dsa.public/meta
testdata/hmac/1
testdata/hmac/1.out
testdata/hmac/2
testdata/hmac/2.out
testdata/hmac/meta
testdata/rsa/1
testdata/rsa/1.out
testdata/rsa/2
testdata/rsa/2.out
testdata/rsa/meta
testdata/rsa-sign/1
testdata/rsa-sign/1.out
testdata/rsa-sign/2
testdata/rsa-sign/2.out
testdata/rsa-sign/meta
testdata/rsa-sign.public/1
testdata/rsa-sign.public/2
testdata/rsa-sign.public/meta
tests/keyczar_tests/__init__.py
