Metadata-Version: 1.0
Name: python-keyczar
Version: 0.71c
Summary: Toolkit for safe and simple cryptography
Home-page: http://www.keyczar.org/
Author: Google, Inc.
Author-email: keyczar-discuss@googlegroups.com
License: http://www.apache.org/licenses/LICENSE-2.0
Platform: any
Classifier: Development Status :: 5 - Production/Stable
Classifier: Intended Audience :: Developers
Classifier: License :: OSI Approved :: Apache Software License
Classifier: Programming Language :: Python
Classifier: Topic :: Security
Classifier: Topic :: Security :: Cryptography
Classifier: Topic :: Software Development :: Libraries :: Python Modules
Classifier: Operating System :: MacOS :: MacOS X
Classifier: Operating System :: Microsoft :: Windows
Classifier: Operating System :: Unix
